chopchopcolorc/README.MD
chopchopcolorc/__init__.py
chopchopcolorc/requirements.txt
chopchopcolorc/thirdparty.json
chopchopcolorc-0.10.dist-info/LICENSE.rst
chopchopcolorc-0.10.dist-info/METADATA
chopchopcolorc-0.10.dist-info/WHEEL
chopchopcolorc-0.10.dist-info/top_level.txt
chopchopcolorc-0.10.dist-info/RECORD
