Metadata-Version: 2.1
Name: chopchopcolorc
Version: 0.10
Summary: Locate RGB colors faster than ever with this efficient color search module (C + multiprocessing)!
Home-page: https://github.com/hansalemaos/chopchopcolorc
Author: Johannes Fischer
Author-email: aulasparticularesdealemaosp@gmail.com
License: MIT
Keywords: multiprocessing,c,rgb
Classifier: Development Status :: 4 - Beta
Classifier: Programming Language :: Python :: 3 :: Only
Classifier: Programming Language :: Python :: 3.10
Classifier: Topic :: Software Development :: Libraries :: Python Modules
Classifier: Topic :: Utilities
License-File: LICENSE.rst
Requires-Dist: a-cv-imwrite-imread-plus
Requires-Dist: locate-pixelcolor-c
Requires-Dist: multiprocca
Requires-Dist: numpy
Requires-Dist: opencv-python
